rubelp-0.1.0.dist-info/METADATA
rubelp-0.1.0.dist-info/WHEEL
rubelp-0.1.0.dist-info/license_files/LICENSE
rubelp/__init__.py
rubelp/__init__.pyi
rubelp/py.typed
rubelp/rubelp.abi3.so
rubelp-0.1.0.dist-info/RECORD
